{
    "poems": [
        {
            "title": "Thơ Bốn Thủ",
            "author": "Nguyễn Thế Thủ",
            "lines": [
                "Con đò bình thủy còn đưa",
                "Dòng sông vẫn đợi người xưa vẫn chờ",
                "Anh về cho đẹp giấc mơ",
                "Của người em gái bên bờ sông hương",
                "",
                "Rồi có mùa xuân nào hoa không nở",
                "Có tâm sự nào buồn như đêm mưa",
                "Có mùa đông nào không giá lạnh",
                "Thì biết tình yêu mấy cho vừa."
            ]
        },
        {
            "title": "Test data 2",
            "author": "Test data 2",
            "lines": [
                "test data 2"
            ]
        }
    ]
}
